sqlglotrs/__init__.py
sqlglotrs/sqlglotrs.cpython-313-darwin.so
sqlglotrs-0.12.0.dist-info/METADATA
sqlglotrs-0.12.0.dist-info/WHEEL
sqlglotrs-0.12.0.dist-info/RECORD
