Metadata-Version: 2.4
Name: sqlglotrs
Version: 0.12.0
Classifier: Programming Language :: Rust
Classifier: Programming Language :: Python :: Implementation :: CPython
Classifier: Programming Language :: Python :: Implementation :: PyPy
Classifier: License :: OSI Approved :: MIT License
Summary: An easily customizable SQL parser and transpiler
Author-email: Toby Mao <toby.mao@gmail.com>
Requires-Python: >=3.9
Project-URL: Homepage, https://github.com/tobymao/sqlglot
Project-URL: Issues, https://github.com/tobymao/sqlglot/issues
